keras_image_classification.py
keras_image_classification_wrapper-0.0.3.dist-info/LICENSE
keras_image_classification_wrapper-0.0.3.dist-info/METADATA
keras_image_classification_wrapper-0.0.3.dist-info/WHEEL
keras_image_classification_wrapper-0.0.3.dist-info/top_level.txt
keras_image_classification_wrapper-0.0.3.dist-info/RECORD
