Metadata-Version: 2.1
Name: keras-image-classification-wrapper
Version: 0.0.3
Summary: A thin wrapper around keras image classification applications.
Home-page: https://github.com/Layerex/keras-image-classification-wrapper
Author: Layerex
Author-email: layerex@dismail.de
License: UNKNOWN
Platform: UNKNOWN
Classifier: Development Status :: 6 - Mature
Classifier: Programming Language :: Python :: 3
Classifier: License :: OSI Approved :: The Unlicense (Unlicense)
Classifier: Operating System :: OS Independent
Classifier: Topic :: Scientific/Engineering :: Artificial Intelligence
Classifier: Topic :: Software Development :: Libraries :: Python Modules
License-File: LICENSE
Requires-Dist: pillow
Requires-Dist: numpy
Requires-Dist: tensorflow
